LICENSE
README.md
setup.py
vk_getter/__init__.py
vk_getter/errors.py
vk_getter/getter.py
vk_getter/models.py
vk_getter.egg-info/PKG-INFO
vk_getter.egg-info/SOURCES.txt
vk_getter.egg-info/dependency_links.txt
vk_getter.egg-info/requires.txt
vk_getter.egg-info/top_level.txt
vk_getter/utils/__init__.py
vk_getter/utils/api.py
vk_getter/utils/tools.py