Metadata-Version: 2.1
Name: vk-getter
Version: 0.0.6
Summary: Getting data from vk.com in a pythonic way.
Author: Crawlic (Nikita Kuznetsov)
Author-email: nikitosik0726@gmail.com
Keywords: python,vk,api,data,images,posts,get
Classifier: Development Status :: 1 - Planning
Classifier: Intended Audience :: Developers
Classifier: Programming Language :: Python :: 3
Classifier: Operating System :: Unix
Classifier: Operating System :: MacOS :: MacOS X
Classifier: Operating System :: Microsoft :: Windows
License-File: LICENSE
